mssql_pyodbc_wrapper/__init__.py
mssql_pyodbc_wrapper/mssqlwrapper.py
mssql_pyodbc_wrapper-1.0.5a0.dist-info/LICENSE
mssql_pyodbc_wrapper-1.0.5a0.dist-info/METADATA
mssql_pyodbc_wrapper-1.0.5a0.dist-info/WHEEL
mssql_pyodbc_wrapper-1.0.5a0.dist-info/top_level.txt
mssql_pyodbc_wrapper-1.0.5a0.dist-info/RECORD
