Metadata-Version: 2.1
Name: mssql-pyodbc-wrapper
Version: 1.0.5a0
Summary: A MSSQL wrapper for pyodbc, with simplified functionality.
Home-page: https://github.com/FABSampaio/mssql-pyodbc-wrapper
Author: Francisco A. B. Sampaio
Author-email: fsampaio@inegi.up.pt
License: UNKNOWN
Project-URL: Bug Reports, https://github.com/pypa/sampleproject/issues
Project-URL: Source, https://github.com/FABSampaio/mssql-pyodbc-wrapper/
Keywords: pyodbc,mssql
Platform: UNKNOWN
Classifier: Development Status :: 3 - Alpha
Classifier: Intended Audience :: Developers
Classifier: Topic :: Software Development
Classifier: License :: OSI Approved :: MIT License
Classifier: Programming Language :: Python :: 3
Classifier: Programming Language :: Python :: 3.6
Classifier: Programming Language :: Python :: 3.7
Classifier: Programming Language :: Python :: 3.8
Classifier: Programming Language :: Python :: 3.9
Classifier: Programming Language :: Python :: 3 :: Only
Requires-Python: >=3.6, <4
License-File: LICENSE
Requires-Dist: pyodbc
Requires-Dist: pandas
